jashin/__init__.py
jashin/dictattr.py
jashin/elapsed.py
jashin/jsondefault.py
jashin/omit.py
jashin/py.typed
jashin-0.0.6.dist-info/LICENSE
jashin-0.0.6.dist-info/METADATA
jashin-0.0.6.dist-info/WHEEL
jashin-0.0.6.dist-info/top_level.txt
jashin-0.0.6.dist-info/RECORD
